{"Stonks": 105, "Player1": 225, "Player2": 310, "Player3": 80, "Player4": 290, "Player5": 190}{"Stonks": 36, "Player1": 73, "Player2": 1044, "Player3": 0, "Player4": 0, "Player5": 43}{"Stonks": 475, "Player1": 95, "Player2": 205, "Player3": 55, "Player4": 195, "Player5": 175}{"Stonks": 280, "Player1": 185, "Player2": 30, "Player3": 185, "Player4": 70, "Player5": 450}{"Stonks": 60, "Player1": 180, "Player2": 210, "Player3": 38, "Player4": 492, "Player5": 220}{"Stonks": 625, "Player1": 0, "Player2": 0, "Player3": 0, "Player4": 172, "Player5": 394}{"Stonks": 123, "Player1": 205, "Player2": 160, "Player3": 180, "Player4": 347, "Player5": 185}{"Stonks": 680, "Player1": 195, "Player2": 65, "Player3": 65, "Player4": 80, "Player5": 115}{"Stonks": 200, "Player1": 440, "Player2": 0, "Player3": 185, "Player4": 160, "Player5": 215}{"Stonks": 170, "Player1": 170, "Player2": 175, "Player3": 240, "Player4": 175, "Player5": 270}