{"Stonks": 48, "Player1": 205, "Player2": 185, "Player3": 312, "Player4": 240, "Player5": 210}{"Stonks": 755, "Player1": 55, "Player2": 170, "Player3": 50, "Player4": 170, "Player5": 0}{"Stonks": 45, "Player1": 50, "Player2": 195, "Player3": 20, "Player4": 645, "Player5": 245}{"Stonks": 35, "Player1": 85, "Player2": 715, "Player3": 115, "Player4": 75, "Player5": 175}{"Stonks": 170, "Player1": 185, "Player2": 265, "Player3": 205, "Player4": 215, "Player5": 160}{"Stonks": 185, "Player1": 195, "Player2": 220, "Player3": 160, "Player4": 250, "Player5": 190}{"Stonks": 40, "Player1": 90, "Player2": 180, "Player3": 575, "Player4": 130, "Player5": 185}{"Stonks": 22, "Player1": 102, "Player2": 215, "Player3": 180, "Player4": 516, "Player5": 165}{"Stonks": 210, "Player1": 200, "Player2": 235, "Player3": 185, "Player4": 200, "Player5": 170}{"Stonks": 185, "Player1": 250, "Player2": 235, "Player3": 190, "Player4": 155, "Player5": 185}